h5mdtools/__init__.py
h5mdtools/h5md_bond_list.py
h5mdtools/h5md_info.py
h5mdtools/h5md_merge.py
h5mdtools/h5md_shrink.py
h5mdtools/h5md_sort.py
h5mdtools/plot_data.py
md_tools/__init__.py
md_tools/_version.py
md_tools/cli.py
md_tools/monomer_purger.py
md_tools/md_libs/__init__.py
md_tools/md_libs/lammps_helper.py
md_tools/md_libs/lammps_utils.py
md_tools/md_libs/files_io/__init__.py
md_tools/md_libs/files_io/files_io.py
md_tools/md_libs/files_io/lammps_reader.py
md_lab_tools-2024.5.0.dist-info/LICENSE.txt
md_lab_tools-2024.5.0.dist-info/METADATA
md_lab_tools-2024.5.0.dist-info/WHEEL
md_lab_tools-2024.5.0.dist-info/entry_points.txt
md_lab_tools-2024.5.0.dist-info/top_level.txt
md_lab_tools-2024.5.0.dist-info/RECORD
