Metadata-Version: 2.1
Name: md-lab-tools
Version: 2024.5.0
Summary: Basic molecular dynamics tools
Author-email: Jakub Krajniak <jkrajniak@gmail.com>, Zidan Zhang <zidan.zhang@utexas.edu>
Classifier: Programming Language :: Python
Requires-Python: >=3.8
License-File: LICENSE.txt
Requires-Dist: numpy >=1.24
Requires-Dist: pandas >=2.0
Requires-Dist: networkx >=3.0
Requires-Dist: click >=8.0
Requires-Dist: h5py >=2.6
